[{
  "_id": {
    "$oid": "65f2ae5b10b0c1551c76f798"
  },
  "content": "First Post",
  "userId": {
    "$oid": "65f1b3baba4cbe924645fd3b"
  },
  "createdAt": {
    "$date": "2024-03-14T07:59:23.458Z"
  },
  "updatedAt": {
    "$date": "2024-03-14T07:59:23.458Z"
  },
  "__v": 0
},
{
  "_id": {
    "$oid": "65f2ae7010b0c1551c76f79a"
  },
  "content": "Second Post",
  "userId": {
    "$oid": "65f1b3baba4cbe924645fd3b"
  },
  "createdAt": {
    "$date": "2024-03-14T07:59:44.316Z"
  },
  "updatedAt": {
    "$date": "2024-03-14T07:59:44.316Z"
  },
  "__v": 0
},
{
  "_id": {
    "$oid": "65f2ae8b31ffb17056eb281a"
  },
  "content": "Third Post",
  "userId": {
    "$oid": "65f1b3baba4cbe924645fd3b"
  },
  "createdAt": {
    "$date": "2024-03-14T08:00:11.572Z"
  },
  "updatedAt": {
    "$date": "2024-03-14T08:00:11.572Z"
  },
  "__v": 0
},
{
  "_id": {
    "$oid": "65f2bec0fb40dab99bd969ab"
  },
  "content": "Post 1",
  "userId": {
    "$oid": "65f1b0e2ba4cbe924645fd0a"
  },
  "createdAt": {
    "$date": "2023-03-21T19:41:29.742Z"
  },
  "updatedAt": {
    "$date": "2022-09-27T18:48:17.238Z"
  },
  "__v": 0
},
{
  "_id": {
    "$oid": "65f2bec0fb40dab99bd969ac"
  },
  "content": "Post 2",
  "userId": {
    "$oid": "65f1b160ba4cbe924645fd21"
  },
  "createdAt": {
    "$date": "2022-07-29T11:10:58.454Z"
  },
  "updatedAt": {
    "$date": "2023-10-07T08:16:45.595Z"
  },
  "__v": 0
},
{
  "_id": {
    "$oid": "65f2bec0fb40dab99bd969ae"
  },
  "content": "Post 4",
  "userId": {
    "$oid": "65f1b139ba4cbe924645fd15"
  },
  "createdAt": {
    "$date": "2021-12-11T04:27:38.380Z"
  },
  "updatedAt": {
    "$date": "2022-10-06T13:41:19.922Z"
  },
  "__v": 0
},
{
  "_id": {
    "$oid": "65f2bec0fb40dab99bd969af"
  },
  "content": "Post 5",
  "userId": {
    "$oid": "65f1b17eba4cbe924645fd26"
  },
  "createdAt": {
    "$date": "2021-08-27T22:57:33.282Z"
  },
  "updatedAt": {
    "$date": "2023-04-17T23:44:40.557Z"
  },
  "__v": 0
},
{
  "_id": {
    "$oid": "65f2bec0fb40dab99bd969b0"
  },
  "content": "Post 6",
  "userId": {
    "$oid": "65f1b152ba4cbe924645fd1d"
  },
  "createdAt": {
    "$date": "2021-05-27T16:19:42.485Z"
  },
  "updatedAt": {
    "$date": "2020-03-26T11:09:06.962Z"
  },
  "__v": 0
},
{
  "_id": {
    "$oid": "65f2bec0fb40dab99bd969b1"
  },
  "content": "Post 7",
  "userId": {
    "$oid": "65f1b377ba4cbe924645fd2e"
  },
  "createdAt": {
    "$date": "2020-06-02T05:19:49.419Z"
  },
  "updatedAt": {
    "$date": "2022-04-30T14:34:28.651Z"
  },
  "__v": 0
},
{
  "_id": {
    "$oid": "65f2bec0fb40dab99bd969b2"
  },
  "content": "Post 8",
  "userId": {
    "$oid": "65f1b353ba4cbe924645fd2a"
  },
  "createdAt": {
    "$date": "2020-03-25T15:45:55.763Z"
  },
  "updatedAt": {
    "$date": "2022-08-07T01:04:03.675Z"
  },
  "__v": 0
},
{
  "_id": {
    "$oid": "65f2bec0fb40dab99bd969b3"
  },
  "content": "Post 9",
  "userId": {
    "$oid": "65f1b0e2ba4cbe924645fd0a"
  },
  "createdAt": {
    "$date": "2023-03-05T03:50:48.699Z"
  },
  "updatedAt": {
    "$date": "2023-02-16T17:47:58.467Z"
  },
  "__v": 0
},
{
  "_id": {
    "$oid": "65f2bec0fb40dab99bd969b4"
  },
  "content": "Post 10",
  "userId": {
    "$oid": "65f1b152ba4cbe924645fd1d"
  },
  "createdAt": {
    "$date": "2020-06-22T12:46:56.406Z"
  },
  "updatedAt": {
    "$date": "2023-04-16T19:00:03.434Z"
  },
  "__v": 0
},
{
  "_id": {
    "$oid": "65f2bec0fb40dab99bd969b5"
  },
  "content": "Post 11",
  "userId": {
    "$oid": "65f1b139ba4cbe924645fd15"
  },
  "createdAt": {
    "$date": "2023-02-28T19:56:08.323Z"
  },
  "updatedAt": {
    "$date": "2020-08-09T09:18:07.809Z"
  },
  "__v": 0
},
{
  "_id": {
    "$oid": "65f2bec0fb40dab99bd969b6"
  },
  "content": "Post 12",
  "userId": {
    "$oid": "65f1b147ba4cbe924645fd19"
  },
  "createdAt": {
    "$date": "2024-03-03T07:16:59.230Z"
  },
  "updatedAt": {
    "$date": "2020-07-12T05:08:27.817Z"
  },
  "__v": 0
},
{
  "_id": {
    "$oid": "65f2bec0fb40dab99bd969b7"
  },
  "content": "Post 13",
  "userId": {
    "$oid": "65f1b160ba4cbe924645fd21"
  },
  "createdAt": {
    "$date": "2020-04-04T23:30:57.919Z"
  },
  "updatedAt": {
    "$date": "2020-04-16T09:52:54.856Z"
  },
  "__v": 0
},
{
  "_id": {
    "$oid": "65f2bec0fb40dab99bd969b8"
  },
  "content": "Post 14",
  "userId": {
    "$oid": "65f1b139ba4cbe924645fd15"
  },
  "createdAt": {
    "$date": "2022-03-26T13:14:19.058Z"
  },
  "updatedAt": {
    "$date": "2024-01-30T06:40:11.653Z"
  },
  "__v": 0
},
{
  "_id": {
    "$oid": "65f2bec0fb40dab99bd969b9"
  },
  "content": "Post 15",
  "userId": {
    "$oid": "65f1b377ba4cbe924645fd2e"
  },
  "createdAt": {
    "$date": "2021-12-14T13:02:08.498Z"
  },
  "updatedAt": {
    "$date": "2023-08-17T20:09:46.247Z"
  },
  "__v": 0
},
{
  "_id": {
    "$oid": "65f2bec0fb40dab99bd969ba"
  },
  "content": "Post 16",
  "userId": {
    "$oid": "65f1b0e2ba4cbe924645fd0a"
  },
  "createdAt": {
    "$date": "2020-04-17T00:44:08.955Z"
  },
  "updatedAt": {
    "$date": "2021-09-01T14:20:47.918Z"
  },
  "__v": 0
},
{
  "_id": {
    "$oid": "65f2bec0fb40dab99bd969bb"
  },
  "content": "Post 17",
  "userId": {
    "$oid": "65f1b17eba4cbe924645fd26"
  },
  "createdAt": {
    "$date": "2024-02-21T00:49:27.199Z"
  },
  "updatedAt": {
    "$date": "2024-02-06T19:14:31.888Z"
  },
  "__v": 0
},
{
  "_id": {
    "$oid": "65f2bec0fb40dab99bd969be"
  },
  "content": "Post 20",
  "userId": {
    "$oid": "65f1b0e2ba4cbe924645fd0a"
  },
  "createdAt": {
    "$date": "2020-03-11T23:26:12.197Z"
  },
  "updatedAt": {
    "$date": "2024-01-17T15:27:42.919Z"
  },
  "__v": 0
},
{
  "_id": {
    "$oid": "65f2bec0fb40dab99bd969bf"
  },
  "content": "Post 21",
  "userId": {
    "$oid": "65f1b152ba4cbe924645fd1d"
  },
  "createdAt": {
    "$date": "2023-10-07T07:45:52.700Z"
  },
  "updatedAt": {
    "$date": "2021-10-20T20:40:12.369Z"
  },
  "__v": 0
},
{
  "_id": {
    "$oid": "65f2bec0fb40dab99bd969c0"
  },
  "content": "Post 22",
  "userId": {
    "$oid": "65f1b0e2ba4cbe924645fd0a"
  },
  "createdAt": {
    "$date": "2023-09-11T20:15:49.885Z"
  },
  "updatedAt": {
    "$date": "2020-12-04T23:14:00.595Z"
  },
  "__v": 0
},
{
  "_id": {
    "$oid": "65f2bec0fb40dab99bd969c1"
  },
  "content": "Post 23",
  "userId": {
    "$oid": "65f1b17eba4cbe924645fd26"
  },
  "createdAt": {
    "$date": "2023-10-31T07:02:31.001Z"
  },
  "updatedAt": {
    "$date": "2020-07-23T15:29:24.537Z"
  },
  "__v": 0
},
{
  "_id": {
    "$oid": "65f2bec0fb40dab99bd969c4"
  },
  "content": "Post 26",
  "userId": {
    "$oid": "65f1b139ba4cbe924645fd15"
  },
  "createdAt": {
    "$date": "2020-04-21T00:28:43.347Z"
  },
  "updatedAt": {
    "$date": "2020-10-24T23:29:50.342Z"
  },
  "__v": 0
},
{
  "_id": {
    "$oid": "65f2bec0fb40dab99bd969c5"
  },
  "content": "Post 27",
  "userId": {
    "$oid": "65f1b160ba4cbe924645fd21"
  },
  "createdAt": {
    "$date": "2024-01-09T02:52:24.578Z"
  },
  "updatedAt": {
    "$date": "2021-05-28T05:52:43.021Z"
  },
  "__v": 0
},
{
  "_id": {
    "$oid": "65f2bec0fb40dab99bd969c6"
  },
  "content": "Post 28",
  "userId": {
    "$oid": "65f1b139ba4cbe924645fd15"
  },
  "createdAt": {
    "$date": "2023-05-23T14:02:49.441Z"
  },
  "updatedAt": {
    "$date": "2024-03-07T01:08:50.185Z"
  },
  "__v": 0
},
{
  "_id": {
    "$oid": "65f2bec0fb40dab99bd969c7"
  },
  "content": "Post 29",
  "userId": {
    "$oid": "65f1b152ba4cbe924645fd1d"
  },
  "createdAt": {
    "$date": "2022-04-10T12:13:21.733Z"
  },
  "updatedAt": {
    "$date": "2024-01-02T12:14:28.455Z"
  },
  "__v": 0
},
{
  "_id": {
    "$oid": "65f2bec0fb40dab99bd969c8"
  },
  "content": "Post 30",
  "userId": {
    "$oid": "65f1b152ba4cbe924645fd1d"
  },
  "createdAt": {
    "$date": "2022-09-13T08:40:58.634Z"
  },
  "updatedAt": {
    "$date": "2021-01-03T15:54:02.614Z"
  },
  "__v": 0
},
{
  "_id": {
    "$oid": "65f2bec0fb40dab99bd969c9"
  },
  "content": "Post 31",
  "userId": {
    "$oid": "65f1b147ba4cbe924645fd19"
  },
  "createdAt": {
    "$date": "2024-02-15T08:56:18.645Z"
  },
  "updatedAt": {
    "$date": "2024-02-18T17:44:27.287Z"
  },
  "__v": 0
},
{
  "_id": {
    "$oid": "65f2bec0fb40dab99bd969ca"
  },
  "content": "Post 32",
  "userId": {
    "$oid": "65f1b160ba4cbe924645fd21"
  },
  "createdAt": {
    "$date": "2021-06-27T19:49:36.888Z"
  },
  "updatedAt": {
    "$date": "2023-02-21T12:29:21.035Z"
  },
  "__v": 0
},
{
  "_id": {
    "$oid": "65f2bec0fb40dab99bd969cb"
  },
  "content": "Post 33",
  "userId": {
    "$oid": "65f1b139ba4cbe924645fd15"
  },
  "createdAt": {
    "$date": "2020-11-10T05:48:21.975Z"
  },
  "updatedAt": {
    "$date": "2021-09-05T16:41:23.380Z"
  },
  "__v": 0
},
{
  "_id": {
    "$oid": "65f2bec0fb40dab99bd969cc"
  },
  "content": "Post 34",
  "userId": {
    "$oid": "65f1b160ba4cbe924645fd21"
  },
  "createdAt": {
    "$date": "2020-08-23T17:54:28.731Z"
  },
  "updatedAt": {
    "$date": "2020-02-20T19:04:06.007Z"
  },
  "__v": 0
},
{
  "_id": {
    "$oid": "65f2bec0fb40dab99bd969cd"
  },
  "content": "Post 35",
  "userId": {
    "$oid": "65f1b152ba4cbe924645fd1d"
  },
  "createdAt": {
    "$date": "2023-05-16T18:39:47.295Z"
  },
  "updatedAt": {
    "$date": "2021-08-12T09:31:44.750Z"
  },
  "__v": 0
},
{
  "_id": {
    "$oid": "65f2bec0fb40dab99bd969cf"
  },
  "content": "Post 37",
  "userId": {
    "$oid": "65f1b17eba4cbe924645fd26"
  },
  "createdAt": {
    "$date": "2023-05-27T12:33:52.554Z"
  },
  "updatedAt": {
    "$date": "2021-10-10T06:02:11.175Z"
  },
  "__v": 0
},
{
  "_id": {
    "$oid": "65f2bec0fb40dab99bd969d0"
  },
  "content": "Post 38",
  "userId": {
    "$oid": "65f1b377ba4cbe924645fd2e"
  },
  "createdAt": {
    "$date": "2021-12-08T16:29:30.574Z"
  },
  "updatedAt": {
    "$date": "2021-05-23T21:09:44.752Z"
  },
  "__v": 0
},
{
  "_id": {
    "$oid": "65f2bec0fb40dab99bd969d1"
  },
  "content": "Post 39",
  "userId": {
    "$oid": "65f1b0e2ba4cbe924645fd0a"
  },
  "createdAt": {
    "$date": "2024-01-29T08:48:40.946Z"
  },
  "updatedAt": {
    "$date": "2020-07-22T15:44:41.503Z"
  },
  "__v": 0
},
{
  "_id": {
    "$oid": "65f2bec0fb40dab99bd969d2"
  },
  "content": "Post 40",
  "userId": {
    "$oid": "65f1b105ba4cbe924645fd11"
  },
  "createdAt": {
    "$date": "2021-09-24T06:35:48.777Z"
  },
  "updatedAt": {
    "$date": "2022-06-17T14:48:58.638Z"
  },
  "__v": 0
},
{
  "_id": {
    "$oid": "65f2bec0fb40dab99bd969d3"
  },
  "content": "Post 41",
  "userId": {
    "$oid": "65f1b17eba4cbe924645fd26"
  },
  "createdAt": {
    "$date": "2020-06-22T02:51:51.573Z"
  },
  "updatedAt": {
    "$date": "2022-01-22T07:28:51.890Z"
  },
  "__v": 0
},
{
  "_id": {
    "$oid": "65f2bec0fb40dab99bd969d4"
  },
  "content": "Post 42",
  "userId": {
    "$oid": "65f1b147ba4cbe924645fd19"
  },
  "createdAt": {
    "$date": "2022-02-04T19:05:03.273Z"
  },
  "updatedAt": {
    "$date": "2023-03-31T04:48:56.168Z"
  },
  "__v": 0
},
{
  "_id": {
    "$oid": "65f2bec0fb40dab99bd969d6"
  },
  "content": "Post 44",
  "userId": {
    "$oid": "65f1b377ba4cbe924645fd2e"
  },
  "createdAt": {
    "$date": "2020-01-03T15:43:27.978Z"
  },
  "updatedAt": {
    "$date": "2021-01-25T00:41:16.777Z"
  },
  "__v": 0
},
{
  "_id": {
    "$oid": "65f2bec0fb40dab99bd969d7"
  },
  "content": "Post 45",
  "userId": {
    "$oid": "65f1b160ba4cbe924645fd21"
  },
  "createdAt": {
    "$date": "2023-01-11T13:46:02.563Z"
  },
  "updatedAt": {
    "$date": "2020-07-04T20:27:31.203Z"
  },
  "__v": 0
},
{
  "_id": {
    "$oid": "65f2bec0fb40dab99bd969d9"
  },
  "content": "Post 50",
  "userId": {
    "$oid": "65f1b147ba4cbe924645fd19"
  },
  "createdAt": {
    "$date": "2022-06-07T20:43:38.338Z"
  },
  "updatedAt": {
    "$date": "2020-10-16T02:00:51.045Z"
  },
  "__v": 0
},
{
  "_id": {
    "$oid": "65f2bec0fb40dab99bd969da"
  },
  "content": "Post 51",
  "userId": {
    "$oid": "65f1b139ba4cbe924645fd15"
  },
  "createdAt": {
    "$date": "2020-08-17T02:59:58.522Z"
  },
  "updatedAt": {
    "$date": "2022-10-24T07:37:49.022Z"
  },
  "__v": 0
},
{
  "_id": {
    "$oid": "65f2bec0fb40dab99bd969db"
  },
  "content": "Post 52",
  "userId": {
    "$oid": "65f1b0e2ba4cbe924645fd0a"
  },
  "createdAt": {
    "$date": "2020-05-06T14:03:02.226Z"
  },
  "updatedAt": {
    "$date": "2022-01-15T20:50:07.414Z"
  },
  "__v": 0
},
{
  "_id": {
    "$oid": "65f2bec0fb40dab99bd969dc"
  },
  "content": "Post 53",
  "userId": {
    "$oid": "65f1b377ba4cbe924645fd2e"
  },
  "createdAt": {
    "$date": "2020-08-06T11:23:59.662Z"
  },
  "updatedAt": {
    "$date": "2020-07-03T18:29:42.516Z"
  },
  "__v": 0
},
{
  "_id": {
    "$oid": "65f2bec0fb40dab99bd969dd"
  },
  "content": "Post 54",
  "userId": {
    "$oid": "65f1b152ba4cbe924645fd1d"
  },
  "createdAt": {
    "$date": "2020-01-27T09:39:21.850Z"
  },
  "updatedAt": {
    "$date": "2024-01-26T17:52:05.489Z"
  },
  "__v": 0
},
{
  "_id": {
    "$oid": "65f2bec0fb40dab99bd969de"
  },
  "content": "Post 55",
  "userId": {
    "$oid": "65f1b139ba4cbe924645fd15"
  },
  "createdAt": {
    "$date": "2021-03-15T21:09:17.292Z"
  },
  "updatedAt": {
    "$date": "2022-08-02T04:32:35.140Z"
  },
  "__v": 0
},
{
  "_id": {
    "$oid": "65f2bec0fb40dab99bd969df"
  },
  "content": "Post 56",
  "userId": {
    "$oid": "65f1b377ba4cbe924645fd2e"
  },
  "createdAt": {
    "$date": "2022-08-16T03:30:46.618Z"
  },
  "updatedAt": {
    "$date": "2021-05-21T07:49:58.669Z"
  },
  "__v": 0
},
{
  "_id": {
    "$oid": "65f2bec0fb40dab99bd969e0"
  },
  "content": "Post 57",
  "userId": {
    "$oid": "65f1b139ba4cbe924645fd15"
  },
  "createdAt": {
    "$date": "2022-10-08T18:21:14.094Z"
  },
  "updatedAt": {
    "$date": "2024-01-12T13:30:28.829Z"
  },
  "__v": 0
},
{
  "_id": {
    "$oid": "65f2bec0fb40dab99bd969e1"
  },
  "content": "Post 58",
  "userId": {
    "$oid": "65f1b152ba4cbe924645fd1d"
  },
  "createdAt": {
    "$date": "2022-05-12T19:10:42.222Z"
  },
  "updatedAt": {
    "$date": "2020-12-04T23:44:54.528Z"
  },
  "__v": 0
},
{
  "_id": {
    "$oid": "65f2bec0fb40dab99bd969e2"
  },
  "content": "Post 59",
  "userId": {
    "$oid": "65f1b0e2ba4cbe924645fd0a"
  },
  "createdAt": {
    "$date": "2023-08-18T02:02:13.739Z"
  },
  "updatedAt": {
    "$date": "2022-05-26T11:52:41.873Z"
  },
  "__v": 0
},
{
  "_id": {
    "$oid": "65f2bec0fb40dab99bd969e3"
  },
  "content": "Post 60",
  "userId": {
    "$oid": "65f1b377ba4cbe924645fd2e"
  },
  "createdAt": {
    "$date": "2020-04-09T22:34:00.632Z"
  },
  "updatedAt": {
    "$date": "2023-11-19T12:29:15.220Z"
  },
  "__v": 0
},
{
  "_id": {
    "$oid": "65f2bec0fb40dab99bd969e4"
  },
  "content": "Post 61",
  "userId": {
    "$oid": "65f1b139ba4cbe924645fd15"
  },
  "createdAt": {
    "$date": "2023-04-06T18:19:28.664Z"
  },
  "updatedAt": {
    "$date": "2021-11-02T20:57:49.684Z"
  },
  "__v": 0
},
{
  "_id": {
    "$oid": "65f2bec0fb40dab99bd969e5"
  },
  "content": "Post 62",
  "userId": {
    "$oid": "65f1b160ba4cbe924645fd21"
  },
  "createdAt": {
    "$date": "2022-03-06T11:35:59.269Z"
  },
  "updatedAt": {
    "$date": "2023-02-22T18:49:26.009Z"
  },
  "__v": 0
},
{
  "_id": {
    "$oid": "65f2bec0fb40dab99bd969e6"
  },
  "content": "Post 63",
  "userId": {
    "$oid": "65f1b0e2ba4cbe924645fd0a"
  },
  "createdAt": {
    "$date": "2022-09-06T10:41:47.437Z"
  },
  "updatedAt": {
    "$date": "2021-11-11T01:00:37.181Z"
  },
  "__v": 0
},
{
  "_id": {
    "$oid": "65f2bec0fb40dab99bd969e7"
  },
  "content": "Post 64",
  "userId": {
    "$oid": "65f1b152ba4cbe924645fd1d"
  },
  "createdAt": {
    "$date": "2022-12-03T15:52:45.608Z"
  },
  "updatedAt": {
    "$date": "2021-04-11T01:47:43.866Z"
  },
  "__v": 0
},
{
  "_id": {
    "$oid": "65f2bec0fb40dab99bd969e8"
  },
  "content": "Post 65",
  "userId": {
    "$oid": "65f1b17eba4cbe924645fd26"
  },
  "createdAt": {
    "$date": "2020-06-26T23:16:32.088Z"
  },
  "updatedAt": {
    "$date": "2022-08-04T07:21:13.362Z"
  },
  "__v": 0
},
{
  "_id": {
    "$oid": "65f2bec0fb40dab99bd969e9"
  },
  "content": "Post 66",
  "userId": {
    "$oid": "65f1b17eba4cbe924645fd26"
  },
  "createdAt": {
    "$date": "2023-02-14T15:30:06.046Z"
  },
  "updatedAt": {
    "$date": "2023-01-30T20:22:38.374Z"
  },
  "__v": 0
},
{
  "_id": {
    "$oid": "65f2bec0fb40dab99bd969ea"
  },
  "content": "Post 67",
  "userId": {
    "$oid": "65f1b147ba4cbe924645fd19"
  },
  "createdAt": {
    "$date": "2023-12-27T19:18:53.349Z"
  },
  "updatedAt": {
    "$date": "2023-05-01T03:46:06.313Z"
  },
  "__v": 0
},
{
  "_id": {
    "$oid": "65f2bec0fb40dab99bd969eb"
  },
  "content": "Post 68",
  "userId": {
    "$oid": "65f1b152ba4cbe924645fd1d"
  },
  "createdAt": {
    "$date": "2021-04-05T13:47:47.129Z"
  },
  "updatedAt": {
    "$date": "2023-12-01T17:55:00.768Z"
  },
  "__v": 0
},
{
  "_id": {
    "$oid": "65f2bec0fb40dab99bd969ec"
  },
  "content": "Post 69",
  "userId": {
    "$oid": "65f1b105ba4cbe924645fd11"
  },
  "createdAt": {
    "$date": "2021-10-03T12:04:14.903Z"
  },
  "updatedAt": {
    "$date": "2022-01-21T04:57:53.264Z"
  },
  "__v": 0
},
{
  "_id": {
    "$oid": "65f2bec0fb40dab99bd969ed"
  },
  "content": "Post 70",
  "userId": {
    "$oid": "65f1b139ba4cbe924645fd15"
  },
  "createdAt": {
    "$date": "2020-12-07T02:07:31.592Z"
  },
  "updatedAt": {
    "$date": "2021-04-13T13:40:04.199Z"
  },
  "__v": 0
},
{
  "_id": {
    "$oid": "65f2bec0fb40dab99bd969ee"
  },
  "content": "Post 71",
  "userId": {
    "$oid": "65f1b377ba4cbe924645fd2e"
  },
  "createdAt": {
    "$date": "2021-04-11T05:52:35.652Z"
  },
  "updatedAt": {
    "$date": "2020-07-03T05:13:18.353Z"
  },
  "__v": 0
},
{
  "_id": {
    "$oid": "65f2bec0fb40dab99bd969ef"
  },
  "content": "Post 72",
  "userId": {
    "$oid": "65f1b353ba4cbe924645fd2a"
  },
  "createdAt": {
    "$date": "2020-04-08T11:43:44.821Z"
  },
  "updatedAt": {
    "$date": "2023-11-10T15:07:41.153Z"
  },
  "__v": 0
},
{
  "_id": {
    "$oid": "65f2bec0fb40dab99bd969f0"
  },
  "content": "Post 73",
  "userId": {
    "$oid": "65f1b160ba4cbe924645fd21"
  },
  "createdAt": {
    "$date": "2023-05-28T07:48:48.903Z"
  },
  "updatedAt": {
    "$date": "2022-03-29T16:52:35.851Z"
  },
  "__v": 0
},
{
  "_id": {
    "$oid": "65f2bec0fb40dab99bd969f1"
  },
  "content": "Post 74",
  "userId": {
    "$oid": "65f1b353ba4cbe924645fd2a"
  },
  "createdAt": {
    "$date": "2021-09-15T18:44:34.886Z"
  },
  "updatedAt": {
    "$date": "2023-05-01T13:22:31.154Z"
  },
  "__v": 0
},
{
  "_id": {
    "$oid": "65f2bec0fb40dab99bd969f2"
  },
  "content": "Post 75",
  "userId": {
    "$oid": "65f1b160ba4cbe924645fd21"
  },
  "createdAt": {
    "$date": "2023-05-10T13:56:55.785Z"
  },
  "updatedAt": {
    "$date": "2022-02-17T09:10:26.579Z"
  },
  "__v": 0
},
{
  "_id": {
    "$oid": "65f2bec0fb40dab99bd969f3"
  },
  "content": "Post 76",
  "userId": {
    "$oid": "65f1b353ba4cbe924645fd2a"
  },
  "createdAt": {
    "$date": "2020-06-22T07:00:32.204Z"
  },
  "updatedAt": {
    "$date": "2021-02-21T23:03:25.584Z"
  },
  "__v": 0
},
{
  "_id": {
    "$oid": "65f2bec0fb40dab99bd969f4"
  },
  "content": "Post 77",
  "userId": {
    "$oid": "65f1b152ba4cbe924645fd1d"
  },
  "createdAt": {
    "$date": "2020-02-12T11:14:20.541Z"
  },
  "updatedAt": {
    "$date": "2021-11-28T11:58:41.107Z"
  },
  "__v": 0
},
{
  "_id": {
    "$oid": "65f2bec0fb40dab99bd969f5"
  },
  "content": "Post 78",
  "userId": {
    "$oid": "65f1b105ba4cbe924645fd11"
  },
  "createdAt": {
    "$date": "2022-07-07T08:25:10.496Z"
  },
  "updatedAt": {
    "$date": "2023-11-09T12:46:08.239Z"
  },
  "__v": 0
},
{
  "_id": {
    "$oid": "65f2bec0fb40dab99bd969f6"
  },
  "content": "Post 79",
  "userId": {
    "$oid": "65f1b17eba4cbe924645fd26"
  },
  "createdAt": {
    "$date": "2021-10-29T05:26:26.405Z"
  },
  "updatedAt": {
    "$date": "2022-01-11T15:22:33.260Z"
  },
  "__v": 0
},
{
  "_id": {
    "$oid": "65f2bec0fb40dab99bd969f7"
  },
  "content": "Post 80",
  "userId": {
    "$oid": "65f1b139ba4cbe924645fd15"
  },
  "createdAt": {
    "$date": "2021-05-30T17:17:19.390Z"
  },
  "updatedAt": {
    "$date": "2020-10-06T06:51:47.798Z"
  },
  "__v": 0
},
{
  "_id": {
    "$oid": "65f2bec0fb40dab99bd969f8"
  },
  "content": "Post 81",
  "userId": {
    "$oid": "65f1b0e2ba4cbe924645fd0a"
  },
  "createdAt": {
    "$date": "2022-05-12T01:56:52.787Z"
  },
  "updatedAt": {
    "$date": "2020-07-03T07:57:58.944Z"
  },
  "__v": 0
},
{
  "_id": {
    "$oid": "65f2bec0fb40dab99bd969f9"
  },
  "content": "Post 82",
  "userId": {
    "$oid": "65f1b17eba4cbe924645fd26"
  },
  "createdAt": {
    "$date": "2023-07-06T03:00:22.923Z"
  },
  "updatedAt": {
    "$date": "2021-01-10T01:20:23.363Z"
  },
  "__v": 0
},
{
  "_id": {
    "$oid": "65f2bec0fb40dab99bd969fa"
  },
  "content": "Post 83",
  "userId": {
    "$oid": "65f1b160ba4cbe924645fd21"
  },
  "createdAt": {
    "$date": "2020-12-02T09:30:20.121Z"
  },
  "updatedAt": {
    "$date": "2021-07-06T09:59:09.907Z"
  },
  "__v": 0
},
{
  "_id": {
    "$oid": "65f2bec0fb40dab99bd969fb"
  },
  "content": "Post 84",
  "userId": {
    "$oid": "65f1b160ba4cbe924645fd21"
  },
  "createdAt": {
    "$date": "2023-09-12T10:00:53.305Z"
  },
  "updatedAt": {
    "$date": "2022-04-14T23:48:04.857Z"
  },
  "__v": 0
},
{
  "_id": {
    "$oid": "65f2bec0fb40dab99bd969fc"
  },
  "content": "Post 85",
  "userId": {
    "$oid": "65f1b147ba4cbe924645fd19"
  },
  "createdAt": {
    "$date": "2021-05-01T12:45:54.646Z"
  },
  "updatedAt": {
    "$date": "2022-11-30T06:15:51.684Z"
  },
  "__v": 0
},
{
  "_id": {
    "$oid": "65f2bec0fb40dab99bd969fd"
  },
  "content": "Post 86",
  "userId": {
    "$oid": "65f1b160ba4cbe924645fd21"
  },
  "createdAt": {
    "$date": "2022-10-09T03:11:32.031Z"
  },
  "updatedAt": {
    "$date": "2021-07-01T11:04:56.984Z"
  },
  "__v": 0
},
{
  "_id": {
    "$oid": "65f2bec0fb40dab99bd969ff"
  },
  "content": "Post 88",
  "userId": {
    "$oid": "65f1b160ba4cbe924645fd21"
  },
  "createdAt": {
    "$date": "2022-03-27T04:30:51.132Z"
  },
  "updatedAt": {
    "$date": "2020-06-27T13:26:48.486Z"
  },
  "__v": 0
},
{
  "_id": {
    "$oid": "65f2bec0fb40dab99bd96a00"
  },
  "content": "Post 89",
  "userId": {
    "$oid": "65f1b377ba4cbe924645fd2e"
  },
  "createdAt": {
    "$date": "2022-06-22T17:56:16.444Z"
  },
  "updatedAt": {
    "$date": "2022-02-15T08:44:16.428Z"
  },
  "__v": 0
},
{
  "_id": {
    "$oid": "65f2bec0fb40dab99bd96a01"
  },
  "content": "Post 90",
  "userId": {
    "$oid": "65f1b17eba4cbe924645fd26"
  },
  "createdAt": {
    "$date": "2022-09-05T07:12:36.781Z"
  },
  "updatedAt": {
    "$date": "2022-08-05T09:45:57.712Z"
  },
  "__v": 0
},
{
  "_id": {
    "$oid": "65f2bec0fb40dab99bd96a02"
  },
  "content": "Post 91",
  "userId": {
    "$oid": "65f1b152ba4cbe924645fd1d"
  },
  "createdAt": {
    "$date": "2022-03-01T22:37:23.512Z"
  },
  "updatedAt": {
    "$date": "2020-08-05T20:33:26.757Z"
  },
  "__v": 0
},
{
  "_id": {
    "$oid": "65f2bec0fb40dab99bd96a03"
  },
  "content": "Post 92",
  "userId": {
    "$oid": "65f1b105ba4cbe924645fd11"
  },
  "createdAt": {
    "$date": "2023-09-21T18:06:52.490Z"
  },
  "updatedAt": {
    "$date": "2021-11-08T02:29:03.794Z"
  },
  "__v": 0
},
{
  "_id": {
    "$oid": "65f2bec0fb40dab99bd96a04"
  },
  "content": "Post 93",
  "userId": {
    "$oid": "65f1b160ba4cbe924645fd21"
  },
  "createdAt": {
    "$date": "2023-12-06T22:19:07.819Z"
  },
  "updatedAt": {
    "$date": "2022-04-06T10:35:42.386Z"
  },
  "__v": 0
},
{
  "_id": {
    "$oid": "65f2bec0fb40dab99bd96a05"
  },
  "content": "Post 94",
  "userId": {
    "$oid": "65f1b147ba4cbe924645fd19"
  },
  "createdAt": {
    "$date": "2021-03-19T17:38:11.495Z"
  },
  "updatedAt": {
    "$date": "2022-04-07T05:58:32.346Z"
  },
  "__v": 0
},
{
  "_id": {
    "$oid": "65f2bec0fb40dab99bd96a06"
  },
  "content": "Post 95",
  "userId": {
    "$oid": "65f1b105ba4cbe924645fd11"
  },
  "createdAt": {
    "$date": "2021-08-04T15:14:16.715Z"
  },
  "updatedAt": {
    "$date": "2020-03-20T19:07:06.083Z"
  },
  "__v": 0
},
{
  "_id": {
    "$oid": "65f2bec0fb40dab99bd96a07"
  },
  "content": "Post 100",
  "userId": {
    "$oid": "65f1b0e2ba4cbe924645fd0a"
  },
  "createdAt": {
    "$date": "2020-02-28T22:44:26.838Z"
  },
  "updatedAt": {
    "$date": "2022-12-22T19:16:35.228Z"
  },
  "__v": 0
}]